src/components/alu.v
module alu(
    input signed [7:0]a,b,
    input areset,
    input [2:0]op,
    output reg signed [7:0] result,
    output reg cf, ovf,
    output z, neg
);

localparam ADDU=0,SUBU=1,ADDS=2,SUBS=3,AND=4,OR=5,XOR=6,SLL=7;

wire [7:0] add_res=$signed(a)+$signed(b);
wire [7:0] sub_res=$signed(a)-$signed(b);

always @(*)begin
  if(areset) begin
    result=8'd0;
    cf=1'b0;
    ovf=1'b0;
  end
  else begin
        result=8'd0;
        cf=1'b0;
        ovf=1'b0;
    case(op)
        ADDU: begin
            {cf,result}={1'b0,a}+{1'b0,b};
         end
        SUBU: begin
            result=a-b;
            if(a>=b) cf=1'b1;
         end
        ADDS:begin
            result=add_res;
            ovf=(a[7]==b[7])&&(add_res[7]!=a[7]);
        end
        SUBS:begin
            result=sub_res;
            ovf=(a[7]!=b[7])&&(sub_res[7]!=a[7]);
        end
        AND: result=a&b;
        OR: result=a|b;
        XOR: result=a^b;
        SLL:begin
            result=a<<1;
            cf=a[7];
        end
        default: begin
            result=8'd0;
            cf=1'b0;
            ovf=1'b0;
        end


    endcase
  end
end

assign neg=result[7];
assign z=!result;

endmodule

tb/alu_tb.v
`timescale 1ps/1ps
module alu_tb;


reg signed [7:0]a,b;
reg areset;
reg [2:0]op;
wire signed [7:0] result;
wire cf, ovf,z,neg;

alu DUT(a,b,areset,op,result,cf,ovf,z,neg);



initial begin
$dumpfile("alu.vcd");
$dumpvars(0,alu_tb);

//start values
areset=1;
a=0;b=0;op=0;

#12 areset=0;

//ADDU
#10 op=0; a=8'd12; b=8'd7; //12+7=19
#10 op=0; a=8'hff; b=8'd1; //cf=1
//SUBU
#10 op=1; a=8'd120; b=8'd50; //120-50=70
#10 op=1; a=8'd50; b=8'd120; //cf=1
//ADDS
#10 op=2; a=8'd127; b=8'd1; //ovf=1
#10 op=2; a= -11; b= -14; // -11 + -14 = -25
//SUBS
#10 op=3; a= -100; b= 100; // ovf=1
#10 op=3; a= -43; b=10; //-43-10=-53
//LOGIC
#10 op=4; a=8'b10011011; b=8'b01010111; //AND
#10 op=5; a=8'b10011011; b=8'b01010111; //OR
#10 op=6; a=8'b10011011; b=8'b01010111; //XOR
#10 op=7; a=8'b11110000; b=8'hff; //SLL


#20 $finish;

end

endmodule

Simulations/alu.vcd
$date
	Thu Oct 23 10:48:41 2025
$end
$version
	Icarus Verilog
$end
$timescale
	1ps
$end
$scope module alu_tb $end
$var wire 1 ! z $end
$var wire 8 " result [7:0] $end
$var wire 1 # ovf $end
$var wire 1 $ neg $end
$var wire 1 % cf $end
$var reg 8 & a [7:0] $end
$var reg 1 ' areset $end
$var reg 8 ( b [7:0] $end
$var reg 3 ) op [2:0] $end
$scope module DUT $end
$var wire 8 * a [7:0] $end
$var wire 1 ' areset $end
$var wire 8 + b [7:0] $end
$var wire 3 , op [2:0] $end
$var wire 1 ! z $end
$var wire 8 - sub_res [7:0] $end
$var wire 1 $ neg $end
$var wire 8 . add_res [7:0] $end
$var parameter 32 / ADDS $end
$var parameter 32 0 ADDU $end
$var parameter 32 1 AND $end
$var parameter 32 2 OR $end
$var parameter 32 3 SLL $end
$var parameter 32 4 SUBS $end
$var parameter 32 5 SUBU $end
$var parameter 32 6 XOR $end
$var reg 1 % cf $end
$var reg 1 # ovf $end
$var reg 8 7 result [7:0] $end
$upscope $end
$upscope $end
$enddefinitions $end
$comment Show the parameter values. $end
$dumpall
b110 6
b1 5
b11 4
b111 3
b101 2
b100 1
b0 0
b10 /
$end
#0
$dumpvars
b0 7
b0 .
b0 -
b0 ,
b0 +
b0 *
b0 )
b0 (
1'
b0 &
0%
0$
0#
b0 "
1!
$end
#12
0'
#22
0!
b10011 "
b10011 7
b111 (
b111 +
b10011 .
b101 -
b1100 &
b1100 *
#32
1%
1!
b0 "
b0 7
b1 (
b1 +
b0 .
b11111110 -
b11111111 &
b11111111 *
#42
0!
b1000110 "
b1000110 7
1%
b110010 (
b110010 +
b10101010 .
b1000110 -
b1111000 &
b1111000 *
b1 )
b1 ,
#52
1$
0%
0!
b10111010 "
b10111010 7
b1111000 (
b1111000 +
b10101010 .
b10111010 -
b110010 &
b110010 *
#62
1#
0!
b10000000 "
b10000000 7
b1 (
b1 +
b10000000 .
b1111110 -
b1111111 &
b1111111 *
b10 )
b10 ,
#72
0#
0!
b11100111 "
b11100111 7
b11110010 (
b11110010 +
b11100111 .
b11 -
b11110101 &
b11110101 *
#82
0$
1#
0!
b111000 "
b111000 7
b1100100 (
b1100100 +
b0 .
b111000 -
b10011100 &
b10011100 *
b11 )
b11 ,
#92
1$
0#
0!
b11001011 "
b11001011 7
b1010 (
b1010 +
b11011111 .
b11001011 -
b11010101 &
b11010101 *
#102
0$
0!
b10011 "
b10011 7
b1010111 (
b1010111 +
b11110010 .
b1000100 -
b10011011 &
b10011011 *
b100 )
b100 ,
#112
1$
0!
b11011111 "
b11011111 7
b101 )
b101 ,
#122
0!
b11001100 "
b11001100 7
b110 )
b110 ,
#132
1%
0!
b11100000 "
b11100000 7
b11111111 (
b11111111 +
b11101111 .
b11110001 -
b11110000 &
b11110000 *
b111 )
b111 ,
