src/components/rf.v
module regfile(
    input clk, areset, we,
    input [2:0] raddr1,raddr2,waddr,
    input [7:0] wdata,
    output [7:0] rout1, rout2
);

reg [7:0]mem[0:7];
integer i;

always @(posedge areset)begin
    if(areset) for(i=0;i<8;i++) mem[i]<=8'd0;
end

always @(negedge clk) begin
    if(we) mem[waddr]<=wdata;
end

assign rout1=mem[raddr1];
assign rout2=mem[raddr2];

endmodule

src/components/ram.v
module ram(
    input clk, areset, en, we,
    input [3:0] addr,
    input [7:0]din,
    output reg [7:0]dout
);

reg [7:0]mem[0:15];
integer i;

always @(posedge clk or posedge areset)begin
    if(areset)begin
        for(i=0;i<16;i++) mem[i]<=8'd0;
        dout<=8'd0;
    end
    else begin
        if(en)begin
            case(we)
            1'b0: dout<=mem[addr];
            1'b1: mem[addr]<=din;
            endcase
        end
    end
end


endmodule

src/components/pc.v
module pc(
    input clk, areset, en, jump,
    input [7:0]jaddr,
    output reg [7:0]pc_value
);

always @(posedge clk or posedge areset)begin
    if(areset) pc_value<=8'd0;
    else if(en)begin
        if(jump) pc_value<=jaddr;
        else pc_value<=pc_value+8'd1;
    end
end

endmodule

src/components/instr_rom.v
module instr_rom(
    input [7:0]addr,
    output [15:0]instr
);

reg [15:0]imem[0:255];

initial begin
    $readmemb("program.mem.txt", imem);
end

assign instr=imem[addr];

endmodule

src/components/controller.v
module controller(
    input [2:0]main_op,
    input [3:0]alu_in,
    input zero,
    output reg [2:0]alu_out,
    output reg [1:0] alusrc,
    output reg en_pc, jump, we_reg, en_ram, we_ram, wrtsrc, rdsrc, pcsrc
);

parameter RTYPE=0, ITYPE=1, LOAD=2, STORE=3, JUMP=4, BEZ=5, BNEZ=6;
parameter ADD=0, SUB=1, AND=2, OR=3, XOR=4;
always @(*)begin
    case(main_op)
    RTYPE:begin
        en_pc=1'b1;
        jump=1'b0;
        we_reg=1'b1;
        case(alu_in)
            ADD:alu_out=3'd0;
            SUB:alu_out=3'd1;
            AND:alu_out=3'd4;
            OR:alu_out=3'd5;
            XOR:alu_out=3'd6;
            default:alu_out=3'd0;
        endcase
        en_ram=1'b0;
        we_ram=1'b0;
        wrtsrc=1'b0;
        rdsrc=1'b1;
        alusrc=2'b0;
        pcsrc=1'bx;
    end
    ITYPE:begin
        en_pc=1'b1;
        jump=1'b0;
        we_reg=1'b1;
        alu_out=3'b0;
        en_ram=1'b0;
        we_ram=1'b0;
        wrtsrc=1'b0;
        rdsrc=1'b1;
        alusrc=2'b01;
        pcsrc=1'bx;
    end
    LOAD:begin
        en_pc=1'b1;
        jump=1'b0;
        we_reg=1'b1;
        alu_out=3'bxxx;
        en_ram=1'b1;
        we_ram=1'b0;
        wrtsrc=1'b1;
        rdsrc=1'bx;
        alusrc=2'bxx;
        pcsrc=1'bx;
    end
    STORE:begin
        en_pc=1'b1;
        jump=1'b0;
        we_reg=1'b0;
        alu_out=3'b0;
        en_ram=1'b1;
        we_ram=1'b1;
        wrtsrc=1'bx;
        rdsrc=1'b0;
        alusrc=2'b10;
        pcsrc=1'bx;
    end
    JUMP:begin
        en_pc=1'b1;
        jump=1'b1;
        we_reg=1'b0;
        alu_out=3'bxxx;
        en_ram=1'b0;
        we_ram=1'bx;
        wrtsrc=1'bx;
        rdsrc=1'bx;
        alusrc=2'bxx;
        pcsrc=1'b1;
    end
    BEZ:begin
        en_pc=1'b1;
        jump=zero;
        we_reg=1'b0;
        alu_out=3'b0;
        en_ram=1'b0;
        we_ram=1'bx;
        wrtsrc=1'bx;
        rdsrc=1'b0;
        alusrc=2'b10;
        pcsrc=1'b0;
    end
    BNEZ:begin
        en_pc=1'b1;
        jump=~zero;
        we_reg=1'b0;
        alu_out=3'b0;
        en_ram=1'b0;
        we_ram=1'bx;
        wrtsrc=1'bx;
        rdsrc=1'b0;
        alusrc=2'b10;
        pcsrc=1'b0;
    end
    default:begin
        en_pc=1'b0;
        jump=1'b0;
        we_reg=1'b0;
        alu_out=3'b0;
        en_ram=1'b0;
        we_ram=1'b0;
        wrtsrc=1'b0;
        rdsrc=1'b0;
        alusrc=2'b0;
        pcsrc=1'b0;
    end
    endcase
end

endmodule

src/components/alu.v
module alu(
    input signed [7:0]a,b,
    input areset,
    input [2:0]op,
    output reg signed [7:0] result,
    output reg cf, ovf,
    output z, neg
);

localparam ADDU=0,SUBU=1,ADDS=2,SUBS=3,AND=4,OR=5,XOR=6,SLL=7;

wire [7:0] add_res=$signed(a)+$signed(b);
wire [7:0] sub_res=$signed(a)-$signed(b);

always @(*)begin
  if(areset) begin
    result=8'd0;
    cf=1'b0;
    ovf=1'b0;
  end
  else begin
        result=8'd0;
        cf=1'b0;
        ovf=1'b0;
    case(op)
        ADDU: begin
            {cf,result}={1'b0,a}+{1'b0,b};
         end
        SUBU: begin
            result=a-b;
            if(a>=b) cf=1'b1;
         end
        ADDS:begin
            result=add_res;
            ovf=(a[7]==b[7])&&(add_res[7]!=a[7]);
        end
        SUBS:begin
            result=sub_res;
            ovf=(a[7]!=b[7])&&(sub_res[7]!=a[7]);
        end
        AND: result=a&b;
        OR: result=a|b;
        XOR: result=a^b;
        SLL:begin
            result=a<<1;
            cf=a[7];
        end
        default: begin
            result=8'd0;
            cf=1'b0;
            ovf=1'b0;
        end


    endcase
  end
end

assign neg=result[7];
assign z=!result;

endmodule

src/cpu.v
module cpu(
    input clk, areset
);

wire [15:0]inst;
wire [7:0]pc_val, jaddr, res_alu, rout1, rout2, b, dout, wdata;
wire [2:0]raddr1, op_alu;
wire [1:0]alusrc;
wire wrtsrc, en_pc, jump, we_reg, z, en_ram, we_ram, rdsrc, pcsrc;

assign raddr1= (rdsrc) ? inst[9:7] : inst[12:10];
assign b= (alusrc==2'b00) ? rout2: (alusrc==2'b01) ? {{1{inst[6]}},inst[6:0]} : 8'b0;
assign wdata= (wrtsrc) ? dout : res_alu;
assign jaddr= (pcsrc) ? inst[12:5] : inst[9:2];

alu alu0(
    .a(rout1),
    .b(b),
    .areset(areset),
    .op(op_alu),
    .result(res_alu),
    .cf(),
    .ovf(),
    .z(z),
    .neg()
    );

controller cont0(
    .main_op(inst[15:13]),
    .alu_in(inst[3:0]),
    .zero(z),
    .alu_out(op_alu),
    .alusrc(alusrc),
    .en_pc(en_pc),
    .jump(jump),
    .we_reg(we_reg),
    .en_ram(en_ram),
    .we_ram(we_ram),
    .wrtsrc(wrtsrc),
    .rdsrc(rdsrc),
    .pcsrc(pcsrc)
);

instr_rom inst0(
    .addr(pc_val),
    .instr(inst)
    );

pc pc0(
    .clk(clk),
    .areset(areset),
    .en(en_pc),
    .jump(jump),
    .jaddr(jaddr),
    .pc_value(pc_val)
    );

ram ram0(
    .clk(clk),
    .areset(areset),
    .en(en_ram),
    .we(we_ram),
    .addr(inst[9:6]),
    .din(res_alu),
    .dout(dout)
    );

regfile rf0(
    .clk(clk),
    .areset(areset),
    .we(we_reg),
    .raddr1(raddr1),
    .raddr2(inst[6:4]),
    .waddr(inst[12:10]),
    .wdata(wdata),
    .rout1(rout1),
    .rout2(rout2)
    );

endmodule

tb/cpu_tb.v
`timescale 1ns/1ps

module cpu_tb;

  reg clk, areset;

  cpu DUT (
    .clk   (clk),
    .areset(areset)
  );

  // ----- ALIASES FOR RAM -----
wire [7:0] RAM0  = DUT.ram0.mem[0];
wire [7:0] RAM1  = DUT.ram0.mem[1];
wire [7:0] RAM2  = DUT.ram0.mem[2];
wire [7:0] RAM3  = DUT.ram0.mem[3];
wire [7:0] RAM4  = DUT.ram0.mem[4];
wire [7:0] RAM5  = DUT.ram0.mem[5];
wire [7:0] RAM6  = DUT.ram0.mem[6];
wire [7:0] RAM7  = DUT.ram0.mem[7];
wire [7:0] RAM8  = DUT.ram0.mem[8];
wire [7:0] RAM9  = DUT.ram0.mem[9];
wire [7:0] RAM10 = DUT.ram0.mem[10];
wire [7:0] RAM11 = DUT.ram0.mem[11];
wire [7:0] RAM12 = DUT.ram0.mem[12];
wire [7:0] RAM13 = DUT.ram0.mem[13];
wire [7:0] RAM14 = DUT.ram0.mem[14];
wire [7:0] RAM15 = DUT.ram0.mem[15];

// ----- ALIASES FOR REGFILE -----
wire [7:0] R0 = DUT.rf0.mem[0];
wire [7:0] R1 = DUT.rf0.mem[1];
wire [7:0] R2 = DUT.rf0.mem[2];
wire [7:0] R3 = DUT.rf0.mem[3];
wire [7:0] R4 = DUT.rf0.mem[4];
wire [7:0] R5 = DUT.rf0.mem[5];
wire [7:0] R6 = DUT.rf0.mem[6];
wire [7:0] R7 = DUT.rf0.mem[7];

  always #5 clk = ~clk;

  always @(posedge clk) begin
    $display("[%0t] PC=%0d  INSTR=%016b", $time, DUT.pc_val, DUT.inst);
  end

  integer i;

  initial begin
    $dumpfile("cpu.vcd");
    $dumpvars(0, cpu_tb);

    clk    = 1'b0;
    areset = 1'b1;

    for (i = 0; i < 16; i = i + 1) DUT.ram0.mem[i] = 8'h00;

    #20 areset = 1'b0;

    repeat (36) @(posedge clk);

    $display("\n==== RAM dump ====");
    for (i = 0; i < 16; i = i + 1)
      $display("RAM[%0d] = 0x%02h", i, DUT.ram0.mem[i]);

    $display("\n==== RegFile dump ====");
    for (i = 0; i < 8; i = i + 1)
      $display("R[%0d] = 0x%02h", i, DUT.rf0.mem[i]);



    #20 $finish;
  end

endmodule

Simulations/cpu.vcd
$date
	Thu Oct 23 17:20:49 2025
$end
$version
	Icarus Verilog
$end
$timescale
	1ps
$end
$scope module cpu_tb $end
$var wire 8 ! R0 [7:0] $end
$var wire 8 " R1 [7:0] $end
$var wire 8 # R2 [7:0] $end
$var wire 8 $ R3 [7:0] $end
$var wire 8 % R4 [7:0] $end
$var wire 8 & R5 [7:0] $end
$var wire 8 ' R6 [7:0] $end
$var wire 8 ( R7 [7:0] $end
$var wire 8 ) RAM0 [7:0] $end
$var wire 8 * RAM1 [7:0] $end
$var wire 8 + RAM10 [7:0] $end
$var wire 8 , RAM11 [7:0] $end
$var wire 8 - RAM12 [7:0] $end
$var wire 8 . RAM13 [7:0] $end
$var wire 8 / RAM14 [7:0] $end
$var wire 8 0 RAM15 [7:0] $end
$var wire 8 1 RAM2 [7:0] $end
$var wire 8 2 RAM3 [7:0] $end
$var wire 8 3 RAM4 [7:0] $end
$var wire 8 4 RAM5 [7:0] $end
$var wire 8 5 RAM6 [7:0] $end
$var wire 8 6 RAM7 [7:0] $end
$var wire 8 7 RAM8 [7:0] $end
$var wire 8 8 RAM9 [7:0] $end
$var reg 1 9 areset $end
$var reg 1 : clk $end
$var integer 32 ; i [31:0] $end
$scope module DUT $end
$var wire 1 9 areset $end
$var wire 1 : clk $end
$var wire 1 < z $end
$var wire 1 = wrtsrc $end
$var wire 1 > we_reg $end
$var wire 1 ? we_ram $end
$var wire 8 @ wdata [7:0] $end
$var wire 8 A rout2 [7:0] $end
$var wire 8 B rout1 [7:0] $end
$var wire 8 C res_alu [7:0] $end
$var wire 1 D rdsrc $end
$var wire 3 E raddr1 [2:0] $end
$var wire 1 F pcsrc $end
$var wire 8 G pc_val [7:0] $end
$var wire 3 H op_alu [2:0] $end
$var wire 1 I jump $end
$var wire 8 J jaddr [7:0] $end
$var wire 16 K inst [15:0] $end
$var wire 1 L en_ram $end
$var wire 1 M en_pc $end
$var wire 8 N dout [7:0] $end
$var wire 8 O b [7:0] $end
$var wire 2 P alusrc [1:0] $end
$scope module alu0 $end
$var wire 1 9 areset $end
$var wire 8 Q b [7:0] $end
$var wire 1 < z $end
$var wire 8 R sub_res [7:0] $end
$var wire 3 S op [2:0] $end
$var wire 1 T neg $end
$var wire 8 U add_res [7:0] $end
$var wire 8 V a [7:0] $end
$var parameter 32 W ADDS $end
$var parameter 32 X ADDU $end
$var parameter 32 Y AND $end
$var parameter 32 Z OR $end
$var parameter 32 [ SLL $end
$var parameter 32 \ SUBS $end
$var parameter 32 ] SUBU $end
$var parameter 32 ^ XOR $end
$var reg 1 _ cf $end
$var reg 1 ` ovf $end
$var reg 8 a result [7:0] $end
$upscope $end
$scope module cont0 $end
$var wire 4 b alu_in [3:0] $end
$var wire 3 c main_op [2:0] $end
$var wire 1 < zero $end
$var parameter 32 d ADD $end
$var parameter 32 e AND $end
$var parameter 32 f BEZ $end
$var parameter 32 g BNEZ $end
$var parameter 32 h ITYPE $end
$var parameter 32 i JUMP $end
$var parameter 32 j LOAD $end
$var parameter 32 k OR $end
$var parameter 32 l RTYPE $end
$var parameter 32 m STORE $end
$var parameter 32 n SUB $end
$var parameter 32 o XOR $end
$var reg 3 p alu_out [2:0] $end
$var reg 2 q alusrc [1:0] $end
$var reg 1 M en_pc $end
$var reg 1 L en_ram $end
$var reg 1 I jump $end
$var reg 1 F pcsrc $end
$var reg 1 D rdsrc $end
$var reg 1 ? we_ram $end
$var reg 1 > we_reg $end
$var reg 1 = wrtsrc $end
$upscope $end
$scope module inst0 $end
$var wire 16 r instr [15:0] $end
$var wire 8 s addr [7:0] $end
$upscope $end
$scope module pc0 $end
$var wire 1 9 areset $end
$var wire 1 : clk $end
$var wire 1 M en $end
$var wire 8 t jaddr [7:0] $end
$var wire 1 I jump $end
$var reg 8 u pc_value [7:0] $end
$upscope $end
$scope module ram0 $end
$var wire 4 v addr [3:0] $end
$var wire 1 9 areset $end
$var wire 1 : clk $end
$var wire 8 w din [7:0] $end
$var wire 1 L en $end
$var wire 1 ? we $end
$var wire 8 x dout [7:0] $end
$var integer 32 y i [31:0] $end
$upscope $end
$scope module rf0 $end
$var wire 1 9 areset $end
$var wire 1 : clk $end
$var wire 3 z raddr1 [2:0] $end
$var wire 3 { raddr2 [2:0] $end
$var wire 8 | rout1 [7:0] $end
$var wire 8 } rout2 [7:0] $end
$var wire 3 ~ waddr [2:0] $end
$var wire 8 !" wdata [7:0] $end
$var wire 1 > we $end
$var integer 32 "" i [31:0] $end
$upscope $end
$upscope $end
$upscope $end
$enddefinitions $end
$comment Show the parameter values. $end
$dumpall
b100 o
b1 n
b11 m
b0 l
b11 k
b10 j
b100 i
b1 h
b110 g
b101 f
b10 e
b0 d
b110 ^
b1 ]
b11 \
b111 [
b101 Z
b100 Y
b0 X
b10 W
$end
#0
$dumpvars
b1000 ""
b0 !"
b0 ~
b0 }
b0 |
b0 {
b0 z
b10000 y
b0 x
b0 w
b0 v
b0 u
b0 t
b0 s
b0 r
b0 q
b0 p
b0 c
b0 b
b0 a
0`
0_
b0 V
b0 U
0T
b0 S
b0 R
b0 Q
b0 P
b0 O
b0 N
1M
0L
b0 K
b0 J
0I
b0 H
b0 G
xF
b0 E
1D
b0 C
b0 B
b0 A
b0 @
0?
1>
0=
1<
b10000 ;
0:
19
b0 8
b0 7
b0 6
b0 5
b0 4
b0 3
b0 2
b0 1
b0 0
b0 /
b0 .
b0 -
b0 ,
b0 +
b0 *
b0 )
b0 (
b0 '
b0 &
b0 %
b0 $
b0 #
b0 "
b0 !
$end
#5000
b10000 y
1:
#10000
0:
#15000
b10000 y
1:
#20000
0:
09
#25000
b10010 @
b10010 !"
0<
b10010 C
b10010 a
b10010 w
b10010 U
b11101110 R
b10010 O
b10010 Q
b1 P
b1 q
b0x00x00 J
b0x00x00 t
b1 ~
b1 {
b10 b
b1 c
b10010000010010 K
b10010000010010 r
b1 G
b1 s
b1 u
1:
#30000
b10010 A
b10010 }
b10010 "
0:
#35000
0<
b10010 C
b10010 a
b10010 w
b10010 B
b10010 V
b10010 |
b1 E
b1 z
b0x00x0 @
b0x00x0 !"
b10010 U
b10010 R
b0 O
b0 Q
b10 P
b10 q
0D
x=
1?
1L
0>
b0x00000 J
b0x00000 t
b0 A
b0 }
b0 {
b0 b
b11 c
b110010000000000 K
b110010000000000 r
b10 G
b10 s
b10 u
1:
#40000
0:
#45000
0<
b100100 C
b100100 a
b100100 w
b100100 U
b0 R
b10010 O
b10010 Q
b100100 @
b100100 !"
b1 P
b1 q
1D
0=
0?
0L
1>
b100100 J
b100100 t
b10010 A
b10010 }
b1 {
b10 v
b10 b
b1 c
b10010 )
b10010010010010 K
b10010010010010 r
b11 G
b11 s
b11 u
1:
#50000
b110110 @
b110110 !"
0<
b110110 C
b110110 a
b110110 w
b10010 R
b110110 U
b100100 B
b100100 V
b100100 |
b100100 A
b100100 }
b100100 "
0:
#55000
0T
b0x00x00 @
b0x00x00 !"
b0 O
b0 Q
0<
b100100 C
b100100 a
b100100 w
b10 P
b10 q
0D
x=
1?
1L
0>
b0xx00x0 J
b0xx00x0 t
b100100 R
b100100 U
b100100 B
b100100 V
b100100 |
b1 E
b1 z
b0 A
b0 }
b100 {
b1 v
b0 b
b11 c
b110010001000000 K
b110010001000000 r
b100 G
b100 s
b100 u
1:
#60000
0:
#65000
0<
b1000010 C
b1000010 a
b1000010 w
b1000010 U
b110 R
b11110 O
b11110 Q
b1000010 @
b1000010 !"
b1 P
b1 q
1D
0=
0?
0L
1>
b1001xx J
b1001xx t
b100100 A
b100100 }
b1 {
b10 v
b1110 b
b1 c
b100100 *
b10010010011110 K
b10010010011110 r
b101 G
b101 s
b101 u
1:
#70000
b1100000 @
b1100000 !"
0<
b1100000 C
b1100000 a
b1100000 w
b100100 R
b1100000 U
b1000010 B
b1000010 V
b1000010 |
b1000010 A
b1000010 }
b1000010 "
0:
#75000
0_
0<
b1000010 C
b1000010 a
b1000010 w
b0x0000x0 @
b0x0000x0 !"
b1000010 U
b1000010 R
b0 O
b0 Q
b10 P
b10 q
0D
x=
1?
1L
0>
b1x0xx0 J
b1x0xx0 t
b0 A
b0 }
b100 {
b11 v
b0 b
b11 c
b110010011000000 K
b110010011000000 r
b110 G
b110 s
b110 u
1:
#80000
0:
#85000
1T
0<
b10000000 C
b10000000 a
b10000000 w
b10000000 U
b100 R
b111110 O
b111110 Q
b10000000 @
b10000000 !"
b1 P
b1 q
1D
0=
0?
0L
1>
b10x1x1 J
b10x1x1 t
b11 {
b10 v
b1110 b
b1 c
b1000010 2
b10010010111110 K
b10010010111110 r
b111 G
b111 s
b111 u
1:
#90000
b10111110 @
b10111110 !"
0<
b10111110 C
b10111110 a
b10111110 w
b1000010 R
b10111110 U
b10000000 B
b10000000 V
b10000000 |
b10000000 "
0:
#95000
1T
bx0000000 @
bx0000000 !"
b0 O
b0 Q
0<
b10000000 C
b10000000 a
b10000000 w
b10 P
b10 q
0D
x=
1?
1L
0>
b0x10xx00 J
b0x10xx00 t
b10000000 R
b10000000 U
b10000000 B
b10000000 V
b10000000 |
b1 E
b1 z
b0 {
b110 v
b0 b
b11 c
b110010110000000 K
b110010110000000 r
b1000 G
b1000 s
b1000 u
1:
#100000
0:
#105000
0T
bx R
bx U
bx B
bx V
bx |
b0x E
b0x z
1<
b0 C
b0 a
b0 w
b10010 @
b10010 !"
bx P
bx q
xD
1=
0?
bx H
bx S
bx p
1>
b0x00000 J
b0x00000 t
b10010 N
b10010 x
b0 v
b10 c
b10000000 5
b100010000000000 K
b100010000000000 r
b1001 G
b1001 s
b1001 u
1:
#110000
b10010 "
0:
#115000
b100100 @
b100100 !"
bx000000 O
bx000000 Q
b100100 N
b100100 x
b0x0x00x0 J
b0x0x00x0 t
b0x0 E
b0x0 z
b10 ~
b100 {
b1 v
b100100001000000 K
b100100001000000 r
b1010 G
b1010 s
b1010 u
1:
#120000
b100100 #
0:
#125000
0T
b11101110 R
b110110 U
b10010 B
b10010 V
b10010 |
b110110 @
b110110 !"
0_
0<
b110110 C
b110110 a
b110110 w
b100100 O
b100100 Q
b0 N
b0 x
b0 P
b0 q
1D
0=
0L
b0 H
b0 S
b0 p
b0x10xx0x J
b0x10xx0x t
b1 E
b1 z
b11 ~
b100100 A
b100100 }
b10 {
b10 v
b0 c
b110010100000 K
b110010100000 r
b1011 G
b1011 s
b1011 u
1:
#130000
b110110 $
0:
#135000
0<
b110110 C
b110110 a
b110110 w
b110110 B
b110110 V
b110110 |
b11 E
b11 z
b0xx0xx0 @
b0xx0xx0 !"
b110110 U
b110110 R
b0 O
b0 Q
b10 P
b10 q
0D
x=
1?
1L
0>
b0x100x00 J
b0x100x00 t
b0 A
b0 }
b0 {
b11 c
b110110010000000 K
b110110010000000 r
b1100 G
b1100 s
b1100 u
1:
#140000
0:
#145000
bx000000 O
bx000000 Q
1<
b0 C
b0 a
b0 w
b1000010 @
b1000010 !"
bx P
bx q
xD
1=
0?
bx H
bx S
bx p
1>
bx0xx0xx0 J
bx0xx0xx0 t
bx R
bx U
bx B
bx V
bx |
bx0x E
bx0x z
b1000010 N
b1000010 x
b100 ~
b100 {
b11 v
b10 c
b110110 1
b101000011000000 K
b101000011000000 r
b1101 G
b1101 s
b1101 u
1:
#150000
bx0000x0 O
bx0000x0 Q
b1000010 A
b1000010 }
b1000010 %
0:
#155000
1T
b11110100 R
b1111000 U
b110110 B
b110110 V
b110110 |
b11110100 @
b11110100 !"
0<
b11110100 C
b11110100 a
b11110100 w
b1000010 O
b1000010 Q
b0 N
b0 x
b0 P
b0 q
1D
0=
0L
b1 H
b1 S
b1 p
bx1xxxx0 J
bx1xxxx0 t
b11 E
b11 z
b101 ~
b111 v
b1 b
b0 c
b1010111000001 K
b1010111000001 r
b1110 G
b1110 s
b1110 u
1:
#160000
b11110100 &
0:
#165000
1T
bx0x00 @
bx0x00 !"
0<
b11110100 C
b11110100 a
b11110100 w
b0 O
b0 Q
b10 P
b10 q
0D
x=
1?
1L
b0 H
b0 S
b0 p
0>
bx0x000 J
bx0x000 t
b11110100 R
b11110100 U
b11110100 B
b11110100 V
b11110100 |
b101 E
b101 z
b0 A
b0 }
b0 {
b100 v
b0 b
b11 c
b111010100000000 K
b111010100000000 r
b1111 G
b1111 s
b1111 u
1:
#170000
0:
#175000
b101 O
b101 Q
1T
0<
b11111001 C
b11111001 a
b11111001 w
b1 P
b1 q
1D
0=
0?
0L
1>
b1xxx0x0x J
b1xxx0x0x t
b11101111 R
b11111001 U
b11110100 B
b11110100 V
b11110100 |
b101 E
b101 z
b11111001 @
b11111001 !"
b110 ~
b1010 v
b101 b
b1 c
b0 N
b0 x
b11101010000101 K
b11101010000101 r
b10000 G
b10000 s
b10000 u
b11110100 3
1:
#180000
b11111001 '
0:
#185000
0_
1T
bx00x @
bx00x !"
b0 O
b0 Q
0<
b11111001 C
b11111001 a
b11111001 w
b10 P
b10 q
0D
x=
1?
1L
0>
bx10xx0x0 J
bx10xx0x0 t
b11111001 R
b11111001 U
b11111001 B
b11111001 V
b11111001 |
b110 E
b110 z
b1000010 A
b1000010 }
b100 {
b101 v
b0 b
b11 c
b111100101000000 K
b111100101000000 r
b10001 G
b10001 s
b10001 u
1:
#190000
0:
#195000
0T
1<
b0 C
b0 a
b0 w
bx P
bx q
xD
1=
0?
bx H
bx S
bx p
1>
bx110xx00 J
bx110xx00 t
bx R
bx U
bx B
bx V
bx |
bx11 E
bx11 z
b10000000 @
b10000000 !"
b111 ~
b0 A
b0 }
b0 {
b110 v
b10 c
b10000000 N
b10000000 x
b101110110000000 K
b101110110000000 r
b10010 G
b10010 s
b10010 u
b11111001 4
1:
#200000
b10000000 (
0:
#205000
0T
b1111001 R
b1111001 U
b11111001 B
b11111001 V
b11111001 |
b1111001 @
b1111001 !"
0<
b1111001 C
b1111001 a
b1111001 w
b10000000 O
b10000000 Q
b0 N
b0 x
b0 P
b0 q
1D
0=
0L
b110 H
b110 S
b110 p
bx11xx1 J
bx11xx1 t
b110 E
b110 z
b1 ~
b10000000 A
b10000000 }
b111 {
b1101 v
b100 b
b0 c
b11101110100 K
b11101110100 r
b10011 G
b10011 s
b10011 u
1:
#210000
b1111001 "
0:
#215000
b0xxxx00x @
b0xxxx00x !"
0<
b1111001 C
b1111001 a
b1111001 w
b0 O
b0 Q
b10 P
b10 q
0D
x=
1?
1L
b0 H
b0 S
b0 p
0>
b0x1xxxx0 J
b0x1xxxx0 t
b1111001 R
b1111001 U
b1111001 B
b1111001 V
b1111001 |
b1 E
b1 z
b1000010 A
b1000010 }
b100 {
b111 v
b0 b
b11 c
b110010111000000 K
b110010111000000 r
b10100 G
b10100 s
b10100 u
1:
#220000
0:
#225000
1T
b10000000 O
b10000000 Q
0<
b11111001 C
b11111001 a
b11111001 w
b11111001 @
b11111001 !"
b0 P
b0 q
1D
0=
0?
0L
b101 H
b101 S
b101 p
1>
b0xxxx1xx J
b0xxxx1xx t
b11111001 R
b11111001 U
b1111001 B
b1111001 V
b1111001 |
b1 E
b1 z
b0 N
b0 x
b10 ~
b10000000 A
b10000000 }
b111 {
b11 v
b11 b
b0 c
b1111001 6
b100011110011 K
b100011110011 r
b10101 G
b10101 s
b10101 u
1:
#230000
b11111001 #
0:
#235000
1T
bx00x @
bx00x !"
0<
b11111001 C
b11111001 a
b11111001 w
b0 O
b0 Q
b10 P
b10 q
0D
x=
1?
1L
b0 H
b0 S
b0 p
0>
bx0x0000 J
bx0x0000 t
b11111001 R
b11111001 U
b11111001 B
b11111001 V
b11111001 |
b10 E
b10 z
b0 A
b0 }
b0 {
b1000 v
b0 b
b11 c
b110101000000000 K
b110101000000000 r
b10110 G
b10110 s
b10110 u
1:
#240000
0:
#245000
1T
b11111001 O
b11111001 Q
0<
b11111001 C
b11111001 a
b11111001 w
b11111001 @
b11111001 !"
b0 P
b0 q
1D
0=
0?
0L
b100 H
b100 S
b100 p
1>
b1xx10xx J
b1xx10xx t
b0 R
b11110010 U
b11111001 B
b11111001 V
b11111001 |
b10 E
b10 z
b0 N
b0 x
b11 ~
b11111001 A
b11111001 }
b110 {
b101 v
b10 b
b0 c
b11111001 7
b110101100010 K
b110101100010 r
b10111 G
b10111 s
b10111 u
1:
#250000
b11111001 $
0:
#255000
1T
bx00x @
bx00x !"
0<
b11111001 C
b11111001 a
b11111001 w
b0 O
b0 Q
b10 P
b10 q
0D
x=
1?
1L
b0 H
b0 S
b0 p
0>
bx100x0 J
bx100x0 t
b11111001 R
b11111001 U
b11111001 B
b11111001 V
b11111001 |
b11 E
b11 z
b1000010 A
b1000010 }
b100 {
b1001 v
b0 b
b11 c
b110111001000000 K
b110111001000000 r
b11000 G
b11000 s
b11000 u
1:
#260000
0:
#265000
b1 O
b1 Q
1T
0<
b11111010 C
b11111010 a
b11111010 w
b11111010 @
b11111010 !"
b1 P
b1 q
1D
0=
0?
0L
1>
bx0xx00 J
bx0xx00 t
b11111000 R
b11111010 U
b11111001 B
b11111001 V
b11111001 |
b11 E
b11 z
b0 N
b0 x
b100 ~
b0 A
b0 }
b0 {
b110 v
b1 b
b1 c
b11111001 8
b11000110000001 K
b11000110000001 r
b11001 G
b11001 s
b11001 u
1:
#270000
b11111010 %
0:
#275000
bx0x0 @
bx0x0 !"
b0 O
b0 Q
0<
b11111010 C
b11111010 a
b11111010 w
b10 P
b10 q
0D
x=
1?
1L
0>
b10xx0x00 J
b10xx0x00 t
b11111010 R
b11111010 U
b11111010 B
b11111010 V
b11111010 |
b100 E
b100 z
b1010 v
b0 b
b11 c
b111001010000000 K
b111001010000000 r
b11010 G
b11010 s
b11010 u
1:
#280000
0:
#285000
b1 O
b1 Q
0<
b11111011 C
b11111011 a
b11111011 w
b11111011 @
b11111011 !"
b1 P
b1 q
1D
0=
0?
0L
1>
b10xx0000 J
b10xx0000 t
b11111001 R
b11111011 U
b11111010 B
b11111010 V
b11111010 |
b100 E
b100 z
b0 N
b0 x
b101 ~
b1000 v
b1 b
b1 c
b11111010 +
b11011000000001 K
b11011000000001 r
b11011 G
b11011 s
b11011 u
1:
#290000
b11111011 &
0:
#295000
0_
bx0xx @
bx0xx !"
b0 O
b0 Q
0<
b11111011 C
b11111011 a
b11111011 w
b10 P
b10 q
0D
x=
1?
1L
0>
b10110xx0 J
b10110xx0 t
b11111011 R
b11111011 U
b11111011 B
b11111011 V
b11111011 |
b101 E
b101 z
b11111010 A
b11111010 }
b100 {
b1011 v
b0 b
b11 c
b111011011000000 K
b111011011000000 r
b11100 G
b11100 s
b11100 u
1:
#300000
0:
#305000
0T
b0 @
b0 !"
bx00x O
bx00x Q
1<
b0 C
b0 a
b0 w
1F
bx P
bx q
xD
x?
0L
bx H
bx S
bx p
1I
b11111 J
b11111 t
bx R
bx U
bx B
bx V
bx |
bx E
bx z
b0 ~
b11111001 A
b11111001 }
b110 {
b1111 v
b100 c
b11111011 ,
b1000001111100000 K
b1000001111100000 r
b11101 G
b11101 s
b11101 u
1:
#310000
0:
#315000
b11111101 U
b11110111 R
1T
b11111101 @
b11111101 !"
0_
0<
b11111101 C
b11111101 a
b11111101 w
b11 O
b11 Q
xF
b1 P
b1 q
1D
0=
0?
b0 H
b0 S
b0 p
1>
0I
b100x0000 J
b100x0000 t
b11111010 B
b11111010 V
b11111010 |
b100 E
b100 z
b100 ~
b0 A
b0 }
b0 {
b1000 v
b11 b
b1 c
b11001000000011 K
b11001000000011 r
b11111 G
b11111 s
b11111 u
1:
#320000
0T
b0 @
b0 !"
1_
1<
b0 C
b0 a
b0 w
b11111010 R
b0 U
b11111101 B
b11111101 V
b11111101 |
b11111101 %
0:
#325000
1T
1I
bx0x @
bx0x !"
b0 O
b0 Q
0<
b11111101 C
b11111101 a
b11111101 w
0_
0F
b10 P
b10 q
0D
x=
x?
0>
b11111 J
b11111 t
b11111101 R
b11111101 U
b11111101 B
b11111101 V
b11111101 |
b100 E
b100 z
b10000000 A
b10000000 }
b111 {
b1 v
b1100 b
b110 c
b1101000001111100 K
b1101000001111100 r
b100000 G
b100000 s
b100000 u
1:
#330000
0:
#335000
0T
1_
1<
b0 C
b0 a
b0 w
b0 U
b11111010 R
b11 O
b11 Q
b0 @
b0 !"
xF
b1 P
b1 q
1D
0=
0?
1>
0I
b100x0000 J
b100x0000 t
b0 A
b0 }
b0 {
b1000 v
b11 b
b1 c
b11001000000011 K
b11001000000011 r
b11111 G
b11111 s
b11111 u
1:
