src/components/instr_rom.v
module instr_rom(
    input [7:0]addr,
    output [15:0]instr
);

reg [15:0]imem[0:255];

initial begin
    $readmemb("program.mem.txt", imem);
end

assign instr=imem[addr];

endmodule

tb/instr_rom_tb.v
`timescale 1ps/1ps
`default_nettype none

module instr_rom_tb;

reg [7:0]addr;
wire [15:0]instr;

instr_rom DUT(addr, instr);

initial begin
    $dumpfile("instr_rom.vcd");
    $dumpvars(0,instr_rom_tb);

    addr=0;
    #10 addr=1;
    #10 addr=2;
    #10 addr=3;
    #10 addr=7;
    #10 addr=13;
    #10 addr=19;
    #10 addr=30;

    #20 $finish;

end

endmodule

Simulations/instr_rom.vcd
$date
	Mon Sep 29 11:01:47 2025
$end
$version
	Icarus Verilog
$end
$timescale
	1ps
$end
$scope module instr_rom_tb $end
$var wire 16 ! instr [15:0] $end
$var reg 8 " addr [7:0] $end
$scope module DUT $end
$var wire 8 # addr [7:0] $end
$var wire 16 $ instr [15:0] $end
$upscope $end
$upscope $end
$enddefinitions $end
$comment Show the parameter values. $end
$dumpall
$end
#0
$dumpvars
b100010000000000 $
b0 #
b0 "
b100010000000000 !
$end
#10
b100100000100000 !
b100100000100000 $
b1 "
b1 #
#20
b110010100000 !
b110010100000 $
b10 "
b10 #
#30
b110110001000000 !
b110110001000000 $
b11 "
b11 #
#40
b11101010000101 !
b11101010000101 $
b111 "
b111 #
#50
b110100100000000 !
b110100100000000 $
b1101 "
b1101 #
#60
b111010101100000 !
b111010101100000 $
b10011 "
b10011 #
#70
bx !
bx $
b11110 "
b11110 #
