src/components/pc.v
module pc(
    input clk, areset, en, jump,
    input [7:0]jaddr,
    output reg [7:0]pc_value
);

always @(posedge clk or posedge areset)begin
    if(areset) pc_value<=8'd0;
    else if(en)begin
        if(jump) pc_value<=jaddr;
        else pc_value<=pc_value+8'd1;
    end
end

endmodule

tb/pc_tb.v
`timescale 1ps/1ps
`default_nettype none

module pc_tb;

reg clk, areset, en, jump;
reg [7:0]jaddr;
wire [7:0]pc_value;

pc DUT(clk, areset, en, jump, jaddr, pc_value);

always #5 clk=~clk;

initial begin
    $dumpfile("pc.vcd");
    $dumpvars(0,pc_tb);

    //Init
    clk=0; areset=1; en=1; jaddr=0; jump=0;
    #12 areset=0; en=1;

    //Increment
    #10 ;
    #10 ;
    #10 en=0;
    #10 en=1;

    //Jump
    #10 jump=1; jaddr=8'h1d;
    #10 jump=0; jaddr=8'hd0;

    //
    #10 jump=1; jaddr=8'hff;
    #10 ;
    #10 jump=0;

    #20 $finish;


end

endmodule

Simulations/pc.vcd
$date
	Mon Sep 29 09:07:41 2025
$end
$version
	Icarus Verilog
$end
$timescale
	1ps
$end
$scope module pc_tb $end
$var wire 8 ! pc_value [7:0] $end
$var reg 1 " areset $end
$var reg 1 # clk $end
$var reg 1 $ en $end
$var reg 8 % jaddr [7:0] $end
$var reg 1 & jump $end
$scope module DUT $end
$var wire 1 " areset $end
$var wire 1 # clk $end
$var wire 1 $ en $end
$var wire 8 ' jaddr [7:0] $end
$var wire 1 & jump $end
$var reg 8 ( pc_value [7:0] $end
$upscope $end
$upscope $end
$enddefinitions $end
$comment Show the parameter values. $end
$dumpall
$end
#0
$dumpvars
b0 (
b0 '
0&
b0 %
1$
0#
1"
b0 !
$end
#5
1#
#10
0#
#12
0"
#15
b1 !
b1 (
1#
#20
0#
#25
b10 !
b10 (
1#
#30
0#
#35
b11 !
b11 (
1#
#40
0#
#42
0$
#45
1#
#50
0#
#52
1$
#55
b100 !
b100 (
1#
#60
0#
#62
b11101 %
b11101 '
1&
#65
b11101 !
b11101 (
1#
#70
0#
#72
b11010000 %
b11010000 '
0&
#75
b11110 !
b11110 (
1#
#80
0#
#82
b11111111 %
b11111111 '
1&
#85
b11111111 !
b11111111 (
1#
#90
0#
#95
1#
#100
0#
#102
0&
#105
b0 !
b0 (
1#
#110
0#
#115
b1 !
b1 (
1#
