src/components/rf.v
module regfile(
    input clk, areset, we,
    input [2:0] raddr1,raddr2,waddr,
    input [7:0] wdata,
    output [7:0] rout1, rout2
);

reg [7:0]mem[0:7];
integer i;

always @(posedge areset)begin
    if(areset) for(i=0;i<8;i++) mem[i]<=8'd0;
end

always @(negedge clk) begin
    if(we) mem[waddr]<=wdata;
end

assign rout1=mem[raddr1];
assign rout2=mem[raddr2];

endmodule

tb/rf_tb.v
`timescale 1ns/1ns

module rf_tb;

    reg clk, areset, we;
    reg [2:0] raddr1, raddr2, waddr;
    reg [7:0] wdata;
    wire [7:0] rout1, rout2;

    regfile DUT (clk, areset, we, raddr1, raddr2, waddr, wdata, rout1, rout2);

    always #5 clk = ~clk;

    initial begin
        $dumpfile("rf.vcd");
        $dumpvars(0, rf_tb);

        // Init
        clk = 0; areset = 1; we = 0;
        raddr1 = 0; raddr2 = 0; waddr = 0; wdata = 0;

        // Reset
        #12 areset = 0;

        // Writing
        @(posedge clk);
        we = 1; waddr = 3; wdata = 8'hAA;
        @(posedge clk);
        we = 1; waddr = 5; wdata = 8'h55;
        @(posedge clk);
        we = 0;

        // Double reading
        raddr1 = 3; raddr2 = 5;

        // Writing & Reading
        @(posedge clk);
        we = 1; waddr = 2; wdata = 8'hF0;
        raddr1 = 2; raddr2 = 3;
        @(posedge clk);
        we = 0;


        // Reset
        @(posedge clk);
        areset = 1;
        @(posedge clk);
        areset = 0;
        raddr1 = 3; raddr2 = 5;

        //Writing with we=0
        #12 wdata=8'hab; waddr=2;
        #10 raddr1=2;

        #20 $finish;
    end

endmodule

Simulations/rf.vcd
$date
	Mon Sep 29 17:40:27 2025
$end
$version
	Icarus Verilog
$end
$timescale
	1ns
$end
$scope module rf_tb $end
$var wire 8 ! rout2 [7:0] $end
$var wire 8 " rout1 [7:0] $end
$var reg 1 # areset $end
$var reg 1 $ clk $end
$var reg 3 % raddr1 [2:0] $end
$var reg 3 & raddr2 [2:0] $end
$var reg 3 ' waddr [2:0] $end
$var reg 8 ( wdata [7:0] $end
$var reg 1 ) we $end
$scope module DUT $end
$var wire 1 # areset $end
$var wire 1 $ clk $end
$var wire 3 * raddr1 [2:0] $end
$var wire 3 + raddr2 [2:0] $end
$var wire 8 , rout1 [7:0] $end
$var wire 8 - rout2 [7:0] $end
$var wire 3 . waddr [2:0] $end
$var wire 8 / wdata [7:0] $end
$var wire 1 ) we $end
$var integer 32 0 i [31:0] $end
$upscope $end
$upscope $end
$enddefinitions $end
$comment Show the parameter values. $end
$dumpall
$end
#0
$dumpvars
b1000 0
b0 /
b0 .
b0 -
b0 ,
b0 +
b0 *
0)
b0 (
b0 '
b0 &
b0 %
0$
1#
b0 "
b0 !
$end
#5
b1000 0
1$
#10
0$
#12
0#
#15
b10101010 (
b10101010 /
b11 '
b11 .
1)
1$
#20
0$
#25
b1010101 (
b1010101 /
b101 '
b101 .
1$
#30
0$
#35
b1010101 !
b1010101 -
b101 &
b101 +
b10101010 "
b10101010 ,
b11 %
b11 *
0)
1$
#40
0$
#45
b10101010 !
b10101010 -
b11 &
b11 +
b11110000 "
b11110000 ,
b10 %
b10 *
b11110000 (
b11110000 /
b10 '
b10 .
1)
1$
#50
0$
#55
0)
1$
#60
0$
#65
b0 !
b0 -
b0 "
b0 ,
b1000 0
1#
1$
#70
0$
#75
b101 &
b101 +
b11 %
b11 *
0#
1$
#80
0$
#85
1$
#87
b10101011 (
b10101011 /
#90
0$
#95
1$
#97
b10 %
b10 *
